{
  "generated_at": "2026-05-19T05:45:05.254Z",
  "charts": {
    "eurusd_5m": {
      "symbol": "EURUSD",
      "timeframe": "5m",
      "current_price": 1.16381,
      "image": "https://www.tradercharts.xyz/eurusd_5m.png",
      "updated_at": "2026-05-19T05:45:20.970Z"
    },
    "eurusd_15m": {
      "symbol": "EURUSD",
      "timeframe": "15m",
      "current_price": 1.16386,
      "image": "https://www.tradercharts.xyz/eurusd_15m.png",
      "updated_at": "2026-05-19T05:45:33.024Z"
    },
    "gbpusd_5m": {
      "symbol": "GBPUSD",
      "timeframe": "5m",
      "current_price": 1.34089,
      "image": "https://www.tradercharts.xyz/gbpusd_5m.png",
      "updated_at": "2026-05-19T05:45:45.658Z"
    },
    "gbpusd_15m": {
      "symbol": "GBPUSD",
      "timeframe": "15m",
      "current_price": 1.3409,
      "image": "https://www.tradercharts.xyz/gbpusd_15m.png",
      "updated_at": "2026-05-19T05:45:57.424Z"
    },
    "usdjpy_5m": {
      "symbol": "USDJPY",
      "timeframe": "5m",
      "current_price": 158.996,
      "image": "https://www.tradercharts.xyz/usdjpy_5m.png",
      "updated_at": "2026-05-19T05:46:09.324Z"
    },
    "usdjpy_15m": {
      "symbol": "USDJPY",
      "timeframe": "15m",
      "current_price": 158.995,
      "image": "https://www.tradercharts.xyz/usdjpy_15m.png",
      "updated_at": "2026-05-19T05:46:21.217Z"
    },
    "btcusd_5m": {
      "symbol": "BTCUSD",
      "timeframe": "5m",
      "current_price": 76861,
      "image": "https://www.tradercharts.xyz/btcusd_5m.png",
      "updated_at": "2026-05-19T05:46:33.866Z"
    },
    "btcusd_15m": {
      "symbol": "BTCUSD",
      "timeframe": "15m",
      "current_price": 76831,
      "image": "https://www.tradercharts.xyz/btcusd_15m.png",
      "updated_at": "2026-05-19T05:46:46.049Z"
    },
    "xauusd_5m": {
      "symbol": "XAUUSD",
      "timeframe": "5m",
      "current_price": 4540.4,
      "image": "https://www.tradercharts.xyz/xauusd_5m.png",
      "updated_at": "2026-05-19T05:46:57.912Z"
    },
    "xauusd_15m": {
      "symbol": "XAUUSD",
      "timeframe": "15m",
      "current_price": 4540.04,
      "image": "https://www.tradercharts.xyz/xauusd_15m.png",
      "updated_at": "2026-05-19T05:47:10.070Z"
    }
  }
}